adengine/__init__.py
adengine/client.py
adengine/engine.py
adengine/messages.py
adengine/pt.py
adengine/server.py
test/__init__.py
test/test_client.py
test/test_engine.py
test/test_pt.py
test/test_stress.py
adengine-0.3.1.dist-info/LICENSE
adengine-0.3.1.dist-info/METADATA
adengine-0.3.1.dist-info/WHEEL
adengine-0.3.1.dist-info/top_level.txt
adengine-0.3.1.dist-info/RECORD
