Metadata-Version: 2.1
Name: adengine
Version: 0.3.1
Summary: Engine for Activity Data Extractor
Home-page: https://git.miem.hse.ru/397/adengine
Author: cher-di
Author-email: cher-di@mail.ru
Maintainer: cher-di
Maintainer-email: cher-di@mail.ru
License: MIT
Platform: Linux
Classifier: License :: OSI Approved :: MIT License
Classifier: Operating System :: POSIX :: Linux
Classifier: Programming Language :: Python :: 3
Classifier: Programming Language :: Python :: 3.8
Requires-Python: >=3.8
Requires-Dist: psutil (>=5.8.0)
Provides-Extra: test
Requires-Dist: pytest ; extra == 'test'
